testprojectelt1/__init__.py
testprojectelt1/base.py
testprojectelt1-0.1.0.dist-info/METADATA
testprojectelt1-0.1.0.dist-info/WHEEL
testprojectelt1-0.1.0.dist-info/top_level.txt
testprojectelt1-0.1.0.dist-info/RECORD
