Metadata-Version: 2.1
Name: testprojectelt1
Version: 0.1.0
Summary: Test project
Author-email: Elliot Su <sodinfeliz@google.com>
Requires-Python: >=3.8
